[{"place_id": 88277571, "licence": "Data \u00a9 OpenStreetMap contributors, ODbL 1.0. http://osm.org/copyright", "osm_type": "way", "osm_id": 697976383, "lat": "48.8535266", "lon": "2.3693946", "class": "highway", "type": "primary", "place_rank": 26, "importance": 0.053426505683985624, "addresstype": "road", "name": "Place de la Bastille", "display_name": "Place de la Bastille, Quartier de la Roquette, 11th Arrondissement, Paris, Metropolitan France, 75011, France", "boundingbox": ["48.8534721", "48.8535529", "2.3692266", "2.3695555"]}]